{"cookies": [{"name": "SESSION", "value": "10224d14-d304-4296-a62a-7b81185f55a7", "domain": "ncas.cmhktry.com", "path": "/cas/", "expires": -1, "httpOnly": true, "secure": false, "sameSite": "Lax"}, {"name": "TGC", "value": "TGT-39579-eQi-zajl9VxQTVzmfExvxnClBRge3Sac06efHUazkVfMADJIkIUfrvM-UaRcWJdQKkAtry2-mita-vt-m-prd-cas003", "domain": "ncas.cmhktry.com", "path": "/cas/", "expires": -1, "httpOnly": true, "secure": false, "sameSite": "Lax"}, {"name": "systemId", "value": "1", "domain": "eoms2.cmhktry.com", "path": "/x5", "expires": -1, "httpOnly": true, "secure": false, "sameSite": "Lax"}, {"name": "JSESSIONID", "value": "82A5F2680AEEDF238CB14A04BDF237FA", "domain": "eoms2.cmhktry.com", "path": "/x5", "expires": -1, "httpOnly": true, "secure": false, "sameSite": "Lax"}, {"name": "org.springframework.web.servlet.i18n.CookieLocaleResolver.LOCALE", "value": "en", "domain": "ncas.cmhktry.com", "path": "/", "expires": -1, "httpOnly": false, "secure": false, "sameSite": "Lax"}, {"name": "zA7uZWGUB1", "value": "tjC7B0zB07XSF0VBR1pVFuGR3MXw1GPFJh2wMQ==", "domain": "ncas.cmhktry.com", "path": "/", "expires": -1, "httpOnly": false, "secure": false, "sameSite": "Lax"}], "origins": []}